{"symbol": "AAV", "v30_markers": [{"time": "2020-03-25", "position": "belowBar", "color": "#76FF03", "shape": "arrowUp", "text": "V30 Buy", "size": 1, "method": "v30"}, {"time": "2020-04-13", "position": "aboveBar", "color": "#4caf50", "shape": "arrowDown", "text": "V30 +2.2%", "size": 1, "method": "v30"}, {"time": "2020-05-14", "position": "belowBar", "color": "#76FF03", "shape": "arrowUp", "text": "V30 Buy", "size": 1, "method": "v30"}, {"time": "2020-07-16", "position": "aboveBar", "color": "#4caf50", "shape": "arrowDown", "text": "V30 +12.1%", "size": 1, "method": "v30"}, {"time": "2020-08-03", "position": "belowBar", "color": "#76FF03", "shape": "arrowUp", "text": "V30 Buy", "size": 1, "method": "v30"}, {"time": "2020-10-19", "position": "aboveBar", "color": "#4caf50", "shape": "arrowDown", "text": "V30 +60.5%", "size": 1, "method": "v30"}, {"time": "2020-11-24", "position": "belowBar", "color": "#76FF03", "shape": "arrowUp", "text": "V30 Buy", "size": 1, "method": "v30"}, {"time": "2020-12-31", "position": "aboveBar", "color": "#4caf50", "shape": "arrowDown", "text": "V30 +105.5% END", "size": 1, "method": "v30"}, {"time": "2021-03-09", "position": "belowBar", "color": "#76FF03", "shape": "arrowUp", "text": "V30 Buy", "size": 1, "method": "v30"}, {"time": "2021-04-20", "position": "aboveBar", "color": "#4caf50", "shape": "arrowDown", "text": "V30 +2.7%", "size": 1, "method": "v30"}, {"time": "2021-06-07", "position": "belowBar", "color": "#76FF03", "shape": "arrowUp", "text": "V30 Buy", "size": 1, "method": "v30"}, {"time": "2021-06-17", "position": "aboveBar", "color": "#f44336", "shape": "arrowDown", "text": "V30 -15.5% HC", "size": 1, "method": "v30"}, {"time": "2021-06-21", "position": "belowBar", "color": "#76FF03", "shape": "arrowUp", "text": "V30 Buy", "size": 1, "method": "v30"}, {"time": "2021-07-12", "position": "aboveBar", "color": "#f44336", "shape": "arrowDown", "text": "V30 -11.1% HC", "size": 1, "method": "v30"}, {"time": "2021-09-14", "position": "belowBar", "color": "#76FF03", "shape": "arrowUp", "text": "V30 Buy", "size": 1, "method": "v30"}, {"time": "2021-11-10", "position": "aboveBar", "color": "#4caf50", "shape": "arrowDown", "text": "V30 +20.1%", "size": 1, "method": "v30"}, {"time": "2021-11-12", "position": "belowBar", "color": "#76FF03", "shape": "arrowUp", "text": "V30 Buy", "size": 1, "method": "v30"}, {"time": "2021-11-24", "position": "aboveBar", "color": "#f44336", "shape": "arrowDown", "text": "V30 -10.3% HC", "size": 1, "method": "v30"}, {"time": "2021-12-24", "position": "belowBar", "color": "#76FF03", "shape": "arrowUp", "text": "V30 Buy", "size": 1, "method": "v30"}, {"time": "2021-12-31", "position": "aboveBar", "color": "#f44336", "shape": "arrowDown", "text": "V30 -4.1% END", "size": 1, "method": "v30"}, {"time": "2022-02-21", "position": "belowBar", "color": "#76FF03", "shape": "arrowUp", "text": "V30 Buy", "size": 1, "method": "v30"}, {"time": "2022-03-10", "position": "aboveBar", "color": "#f44336", "shape": "arrowDown", "text": "V30 -10.2% HC", "size": 1, "method": "v30"}, {"time": "2022-06-27", "position": "belowBar", "color": "#76FF03", "shape": "arrowUp", "text": "V30 Buy", "size": 1, "method": "v30"}, {"time": "2022-07-26", "position": "aboveBar", "color": "#4caf50", "shape": "arrowDown", "text": "V30 +0.0%", "size": 1, "method": "v30"}, {"time": "2022-08-09", "position": "belowBar", "color": "#76FF03", "shape": "arrowUp", "text": "V30 Buy", "size": 1, "method": "v30"}, {"time": "2022-08-25", "position": "aboveBar", "color": "#f44336", "shape": "arrowDown", "text": "V30 -2.1%", "size": 1, "method": "v30"}, {"time": "2022-11-18", "position": "belowBar", "color": "#76FF03", "shape": "arrowUp", "text": "V30 Buy", "size": 1, "method": "v30"}, {"time": "2022-12-28", "position": "aboveBar", "color": "#4caf50", "shape": "arrowDown", "text": "V30 +19.4%", "size": 1, "method": "v30"}, {"time": "2023-02-20", "position": "belowBar", "color": "#76FF03", "shape": "arrowUp", "text": "V30 Buy", "size": 1, "method": "v30"}, {"time": "2023-03-01", "position": "aboveBar", "color": "#f44336", "shape": "arrowDown", "text": "V30 -13.3% HC", "size": 1, "method": "v30"}, {"time": "2023-04-17", "position": "belowBar", "color": "#76FF03", "shape": "arrowUp", "text": "V30 Buy", "size": 1, "method": "v30"}, {"time": "2023-07-03", "position": "aboveBar", "color": "#4caf50", "shape": "arrowDown", "text": "V30 +25.0%", "size": 1, "method": "v30"}, {"time": "2023-07-17", "position": "belowBar", "color": "#76FF03", "shape": "arrowUp", "text": "V30 Buy", "size": 1, "method": "v30"}, {"time": "2023-08-24", "position": "aboveBar", "color": "#f44336", "shape": "arrowDown", "text": "V30 -6.3%", "size": 1, "method": "v30"}, {"time": "2024-02-22", "position": "belowBar", "color": "#76FF03", "shape": "arrowUp", "text": "V30 Buy", "size": 1, "method": "v30"}, {"time": "2024-03-05", "position": "aboveBar", "color": "#f44336", "shape": "arrowDown", "text": "V30 -7.3%", "size": 1, "method": "v30"}, {"time": "2024-05-07", "position": "belowBar", "color": "#76FF03", "shape": "arrowUp", "text": "V30 Buy", "size": 1, "method": "v30"}, {"time": "2024-06-26", "position": "aboveBar", "color": "#f44336", "shape": "arrowDown", "text": "V30 -1.8%", "size": 1, "method": "v30"}, {"time": "2024-08-19", "position": "belowBar", "color": "#76FF03", "shape": "arrowUp", "text": "V30 Buy", "size": 1, "method": "v30"}, {"time": "2024-10-02", "position": "aboveBar", "color": "#4caf50", "shape": "arrowDown", "text": "V30 +6.7%", "size": 1, "method": "v30"}, {"time": "2024-11-26", "position": "belowBar", "color": "#76FF03", "shape": "arrowUp", "text": "V30 Buy", "size": 1, "method": "v30"}, {"time": "2024-12-19", "position": "aboveBar", "color": "#4caf50", "shape": "arrowDown", "text": "V30 +11.8% PP", "size": 1, "method": "v30"}, {"time": "2024-12-20", "position": "belowBar", "color": "#76FF03", "shape": "arrowUp", "text": "V30 Buy", "size": 1, "method": "v30"}, {"time": "2024-12-31", "position": "aboveBar", "color": "#f44336", "shape": "arrowDown", "text": "V30 -5.2% END", "size": 1, "method": "v30"}, {"time": "2025-02-17", "position": "belowBar", "color": "#76FF03", "shape": "arrowUp", "text": "V30 Buy", "size": 1, "method": "v30"}, {"time": "2025-02-28", "position": "aboveBar", "color": "#f44336", "shape": "arrowDown", "text": "V30 -5.5%", "size": 1, "method": "v30"}, {"time": "2025-04-15", "position": "belowBar", "color": "#76FF03", "shape": "arrowUp", "text": "V30 Buy", "size": 1, "method": "v30"}, {"time": "2025-06-03", "position": "aboveBar", "color": "#4caf50", "shape": "arrowDown", "text": "V30 +25.0%", "size": 1, "method": "v30"}, {"time": "2025-07-11", "position": "belowBar", "color": "#76FF03", "shape": "arrowUp", "text": "V30 Buy", "size": 1, "method": "v30"}, {"time": "2025-07-23", "position": "aboveBar", "color": "#f44336", "shape": "arrowDown", "text": "V30 -1.5%", "size": 1, "method": "v30"}, {"time": "2025-10-01", "position": "belowBar", "color": "#76FF03", "shape": "arrowUp", "text": "V30 Buy", "size": 1, "method": "v30"}, {"time": "2025-10-13", "position": "aboveBar", "color": "#f44336", "shape": "arrowDown", "text": "V30 -1.7%", "size": 1, "method": "v30"}, {"time": "2025-10-29", "position": "belowBar", "color": "#76FF03", "shape": "arrowUp", "text": "V30 Buy", "size": 1, "method": "v30"}, {"time": "2025-12-18", "position": "aboveBar", "color": "#4caf50", "shape": "arrowDown", "text": "V30 +1.6%", "size": 1, "method": "v30"}], "v30_trades": [{"entry_date": "2020-03-25", "exit_date": "2020-04-13", "pnl_pct": 2.23, "holding_days": 12, "exit_reason": "signal", "entry_trend": "weak", "quick_reentry": false, "breakout_entry": false, "vshape_entry": true, "entry_profile": "high_beta", "entry_choppy_regime": false, "position_size": 0.262395}, {"entry_date": "2020-05-14", "exit_date": "2020-07-16", "pnl_pct": 12.14, "holding_days": 45, "exit_reason": "signal", "entry_trend": "weak", "quick_reentry": false, "breakout_entry": false, "vshape_entry": true, "entry_profile": "high_beta", "entry_choppy_regime": false, "position_size": 0.3332}, {"entry_date": "2020-08-03", "exit_date": "2020-10-19", "pnl_pct": 60.55, "holding_days": 54, "exit_reason": "signal", "entry_trend": "weak", "quick_reentry": false, "breakout_entry": false, "vshape_entry": true, "entry_profile": "high_beta", "entry_choppy_regime": false, "position_size": 0.262395}, {"entry_date": "2020-11-24", "exit_date": "2020-12-31", "pnl_pct": 105.55, "holding_days": 27, "exit_reason": "end", "entry_trend": "weak", "quick_reentry": false, "breakout_entry": true, "vshape_entry": false, "entry_profile": "high_beta", "entry_choppy_regime": false, "position_size": 0.25}, {"entry_date": "2021-03-09", "exit_date": "2021-04-20", "pnl_pct": 2.69, "holding_days": 30, "exit_reason": "signal", "entry_trend": "strong", "quick_reentry": false, "breakout_entry": false, "vshape_entry": false, "entry_profile": "high_beta", "entry_choppy_regime": false, "position_size": 0.3123749999999999}, {"entry_date": "2021-06-07", "exit_date": "2021-06-17", "pnl_pct": -15.54, "holding_days": 8, "exit_reason": "signal_hard_cap", "entry_trend": "strong", "quick_reentry": false, "breakout_entry": false, "vshape_entry": false, "entry_profile": "high_beta", "entry_choppy_regime": false, "position_size": 0.3332}, {"entry_date": "2021-06-21", "exit_date": "2021-07-12", "pnl_pct": -11.1, "holding_days": 15, "exit_reason": "signal_hard_cap", "entry_trend": "strong", "quick_reentry": false, "breakout_entry": false, "vshape_entry": false, "entry_profile": "high_beta", "entry_choppy_regime": false, "position_size": 0.262395}, {"entry_date": "2021-09-14", "exit_date": "2021-11-10", "pnl_pct": 20.15, "holding_days": 41, "exit_reason": "signal", "entry_trend": "strong", "quick_reentry": false, "breakout_entry": false, "vshape_entry": false, "entry_profile": "high_beta", "entry_choppy_regime": false, "position_size": 0.25}, {"entry_date": "2021-11-12", "exit_date": "2021-11-24", "pnl_pct": -10.28, "holding_days": 8, "exit_reason": "signal_hard_cap", "entry_trend": "strong", "quick_reentry": false, "breakout_entry": false, "vshape_entry": false, "entry_profile": "high_beta", "entry_choppy_regime": false, "position_size": 0.3332}, {"entry_date": "2021-12-24", "exit_date": "2021-12-31", "pnl_pct": -4.08, "holding_days": 5, "exit_reason": "end", "entry_trend": "weak", "quick_reentry": false, "breakout_entry": false, "vshape_entry": true, "entry_profile": "high_beta", "entry_choppy_regime": false, "position_size": 0.3332}, {"entry_date": "2022-02-21", "exit_date": "2022-03-10", "pnl_pct": -10.15, "holding_days": 13, "exit_reason": "signal_hard_cap", "entry_trend": "strong", "quick_reentry": false, "breakout_entry": false, "vshape_entry": false, "entry_profile": "high_beta", "entry_choppy_regime": false, "position_size": 0.4165}, {"entry_date": "2022-06-27", "exit_date": "2022-07-26", "pnl_pct": 0.0, "holding_days": 21, "exit_reason": "signal", "entry_trend": "weak", "quick_reentry": false, "breakout_entry": false, "vshape_entry": true, "entry_profile": "high_beta", "entry_choppy_regime": false, "position_size": 0.262395}, {"entry_date": "2022-08-09", "exit_date": "2022-08-25", "pnl_pct": -2.08, "holding_days": 12, "exit_reason": "signal", "entry_trend": "strong", "quick_reentry": false, "breakout_entry": false, "vshape_entry": false, "entry_profile": "high_beta", "entry_choppy_regime": false, "position_size": 0.3675}, {"entry_date": "2022-11-18", "exit_date": "2022-12-28", "pnl_pct": 19.44, "holding_days": 28, "exit_reason": "signal", "entry_trend": "weak", "quick_reentry": false, "breakout_entry": false, "vshape_entry": true, "entry_profile": "high_beta", "entry_choppy_regime": false, "position_size": 0.262395}, {"entry_date": "2023-02-20", "exit_date": "2023-03-01", "pnl_pct": -13.33, "holding_days": 7, "exit_reason": "signal_hard_cap", "entry_trend": "weak", "quick_reentry": false, "breakout_entry": false, "vshape_entry": true, "entry_profile": "high_beta", "entry_choppy_regime": false, "position_size": 0.262395}, {"entry_date": "2023-04-17", "exit_date": "2023-07-03", "pnl_pct": 25.0, "holding_days": 52, "exit_reason": "signal", "entry_trend": "strong", "quick_reentry": false, "breakout_entry": false, "vshape_entry": false, "entry_profile": "high_beta", "entry_choppy_regime": false, "position_size": 0.3123749999999999}, {"entry_date": "2023-07-17", "exit_date": "2023-08-24", "pnl_pct": -6.35, "holding_days": 28, "exit_reason": "signal", "entry_trend": "strong", "quick_reentry": false, "breakout_entry": false, "vshape_entry": false, "entry_profile": "high_beta", "entry_choppy_regime": false, "position_size": 0.4165}, {"entry_date": "2024-02-22", "exit_date": "2024-03-05", "pnl_pct": -7.32, "holding_days": 8, "exit_reason": "signal", "entry_trend": "moderate", "quick_reentry": false, "breakout_entry": true, "vshape_entry": false, "entry_profile": "high_beta", "entry_choppy_regime": false, "position_size": 0.4165}, {"entry_date": "2024-05-07", "exit_date": "2024-06-26", "pnl_pct": -1.75, "holding_days": 36, "exit_reason": "signal", "entry_trend": "strong", "quick_reentry": false, "breakout_entry": false, "vshape_entry": false, "entry_profile": "high_beta", "entry_choppy_regime": false, "position_size": 0.25}, {"entry_date": "2024-08-19", "exit_date": "2024-10-02", "pnl_pct": 6.67, "holding_days": 30, "exit_reason": "signal", "entry_trend": "moderate", "quick_reentry": false, "breakout_entry": false, "vshape_entry": false, "entry_profile": "high_beta", "entry_choppy_regime": false, "position_size": 0.3123749999999999}, {"entry_date": "2024-11-26", "exit_date": "2024-12-19", "pnl_pct": 11.76, "holding_days": 17, "exit_reason": "peak_protect_dist", "entry_trend": "moderate", "quick_reentry": false, "breakout_entry": false, "vshape_entry": false, "entry_profile": "high_beta", "entry_choppy_regime": false, "position_size": 0.3123749999999999}, {"entry_date": "2024-12-20", "exit_date": "2024-12-31", "pnl_pct": -5.19, "holding_days": 7, "exit_reason": "end", "entry_trend": "strong", "quick_reentry": false, "breakout_entry": false, "vshape_entry": false, "entry_profile": "high_beta", "entry_choppy_regime": false, "position_size": 0.4165}, {"entry_date": "2025-02-17", "exit_date": "2025-02-28", "pnl_pct": -5.48, "holding_days": 9, "exit_reason": "signal", "entry_trend": "moderate", "quick_reentry": false, "breakout_entry": true, "vshape_entry": false, "entry_profile": "high_beta", "entry_choppy_regime": false, "position_size": 0.49}, {"entry_date": "2025-04-15", "exit_date": "2025-06-03", "pnl_pct": 25.0, "holding_days": 32, "exit_reason": "signal", "entry_trend": "weak", "quick_reentry": false, "breakout_entry": false, "vshape_entry": true, "entry_profile": "high_beta", "entry_choppy_regime": false, "position_size": 0.262395}, {"entry_date": "2025-07-11", "exit_date": "2025-07-23", "pnl_pct": -1.47, "holding_days": 8, "exit_reason": "signal", "entry_trend": "weak", "quick_reentry": false, "breakout_entry": true, "vshape_entry": false, "entry_profile": "high_beta", "entry_choppy_regime": false, "position_size": 0.294}, {"entry_date": "2025-10-01", "exit_date": "2025-10-13", "pnl_pct": -1.69, "holding_days": 8, "exit_reason": "signal", "entry_trend": "weak", "quick_reentry": false, "breakout_entry": true, "vshape_entry": false, "entry_profile": "high_beta", "entry_choppy_regime": false, "position_size": 0.294}, {"entry_date": "2025-10-29", "exit_date": "2025-12-18", "pnl_pct": 1.59, "holding_days": 36, "exit_reason": "signal", "entry_trend": "moderate", "quick_reentry": false, "breakout_entry": true, "vshape_entry": false, "entry_profile": "high_beta", "entry_choppy_regime": false, "position_size": 0.4165}], "v30_stats": {"total_trades": 27, "wins": 12, "losses": 15, "win_rate": 44.4, "total_pnl_pct": 197.0, "avg_pnl_pct": 7.29, "median_pnl_pct": -1.47, "std_pnl_pct": 24.86, "avg_win_pct": 24.4, "avg_loss_pct": -6.39, "payoff_ratio": 3.82, "max_win_pct": 105.55, "max_loss_pct": -15.54, "avg_hold": 22.1, "pf": 3.06, "version": "v30"}}