{"symbol": "AMS", "v27_markers": [{"time": "2021-03-19", "position": "belowBar", "color": "#9C27B0", "shape": "arrowUp", "text": "V27 Buy", "size": 1, "method": "v27"}, {"time": "2021-04-22", "position": "aboveBar", "color": "#f44336", "shape": "arrowDown", "text": "V27 -3.3%", "size": 1, "method": "v27"}, {"time": "2021-06-17", "position": "belowBar", "color": "#9C27B0", "shape": "arrowUp", "text": "V27 Buy", "size": 1, "method": "v27"}, {"time": "2021-07-01", "position": "aboveBar", "color": "#f44336", "shape": "arrowDown", "text": "V27 -7.2%", "size": 1, "method": "v27"}, {"time": "2021-09-10", "position": "belowBar", "color": "#9C27B0", "shape": "arrowUp", "text": "V27 Buy", "size": 1, "method": "v27"}, {"time": "2021-10-11", "position": "aboveBar", "color": "#4caf50", "shape": "arrowDown", "text": "V27 +6.5%", "size": 1, "method": "v27"}, {"time": "2021-10-19", "position": "belowBar", "color": "#9C27B0", "shape": "arrowUp", "text": "V27 Buy", "size": 1, "method": "v27"}, {"time": "2021-11-09", "position": "aboveBar", "color": "#f44336", "shape": "arrowDown", "text": "V27 -0.6%", "size": 1, "method": "v27"}, {"time": "2021-11-15", "position": "belowBar", "color": "#9C27B0", "shape": "arrowUp", "text": "V27 Buy", "size": 1, "method": "v27"}, {"time": "2021-11-24", "position": "aboveBar", "color": "#f44336", "shape": "arrowDown", "text": "V27 -12.6% HC", "size": 1, "method": "v27"}, {"time": "2022-02-22", "position": "belowBar", "color": "#9C27B0", "shape": "arrowUp", "text": "V27 Buy", "size": 1, "method": "v27"}, {"time": "2022-03-28", "position": "aboveBar", "color": "#f44336", "shape": "arrowDown", "text": "V27 -2.4%", "size": 1, "method": "v27"}, {"time": "2022-05-20", "position": "belowBar", "color": "#9C27B0", "shape": "arrowUp", "text": "V27 Buy", "size": 1, "method": "v27"}, {"time": "2022-06-17", "position": "aboveBar", "color": "#4caf50", "shape": "arrowDown", "text": "V27 +1.0%", "size": 1, "method": "v27"}, {"time": "2023-02-03", "position": "belowBar", "color": "#9C27B0", "shape": "arrowUp", "text": "V27 Buy", "size": 1, "method": "v27"}, {"time": "2023-04-10", "position": "aboveBar", "color": "#4caf50", "shape": "arrowDown", "text": "V27 +54.3%", "size": 1, "method": "v27"}, {"time": "2023-05-16", "position": "belowBar", "color": "#9C27B0", "shape": "arrowUp", "text": "V27 Buy", "size": 1, "method": "v27"}, {"time": "2023-06-20", "position": "aboveBar", "color": "#4caf50", "shape": "arrowDown", "text": "V27 +5.8%", "size": 1, "method": "v27"}, {"time": "2023-08-04", "position": "belowBar", "color": "#9C27B0", "shape": "arrowUp", "text": "V27 Buy", "size": 1, "method": "v27"}, {"time": "2023-08-28", "position": "aboveBar", "color": "#4caf50", "shape": "arrowDown", "text": "V27 +0.8%", "size": 1, "method": "v27"}, {"time": "2023-12-07", "position": "belowBar", "color": "#9C27B0", "shape": "arrowUp", "text": "V27 Buy", "size": 1, "method": "v27"}, {"time": "2023-12-21", "position": "aboveBar", "color": "#f44336", "shape": "arrowDown", "text": "V27 -1.9%", "size": 1, "method": "v27"}, {"time": "2024-02-22", "position": "belowBar", "color": "#9C27B0", "shape": "arrowUp", "text": "V27 Buy", "size": 1, "method": "v27"}, {"time": "2024-03-07", "position": "aboveBar", "color": "#f44336", "shape": "arrowDown", "text": "V27 -1.9%", "size": 1, "method": "v27"}, {"time": "2024-03-25", "position": "belowBar", "color": "#9C27B0", "shape": "arrowUp", "text": "V27 Buy", "size": 1, "method": "v27"}, {"time": "2024-04-22", "position": "aboveBar", "color": "#f44336", "shape": "arrowDown", "text": "V27 -1.0%", "size": 1, "method": "v27"}, {"time": "2024-06-17", "position": "belowBar", "color": "#9C27B0", "shape": "arrowUp", "text": "V27 Buy", "size": 1, "method": "v27"}, {"time": "2024-07-04", "position": "aboveBar", "color": "#4caf50", "shape": "arrowDown", "text": "V27 +6.4%", "size": 1, "method": "v27"}, {"time": "2024-07-09", "position": "belowBar", "color": "#9C27B0", "shape": "arrowUp", "text": "V27 Buy", "size": 1, "method": "v27"}, {"time": "2024-07-26", "position": "aboveBar", "color": "#f44336", "shape": "arrowDown", "text": "V27 -9.8%", "size": 1, "method": "v27"}, {"time": "2025-02-25", "position": "belowBar", "color": "#9C27B0", "shape": "arrowUp", "text": "V27 Buy", "size": 1, "method": "v27"}, {"time": "2025-03-10", "position": "aboveBar", "color": "#f44336", "shape": "arrowDown", "text": "V27 -6.7%", "size": 1, "method": "v27"}, {"time": "2025-04-11", "position": "belowBar", "color": "#9C27B0", "shape": "arrowUp", "text": "V27 Buy", "size": 1, "method": "v27"}, {"time": "2025-04-22", "position": "aboveBar", "color": "#f44336", "shape": "arrowDown", "text": "V27 -11.8% HC", "size": 1, "method": "v27"}, {"time": "2025-06-16", "position": "belowBar", "color": "#9C27B0", "shape": "arrowUp", "text": "V27 Buy", "size": 1, "method": "v27"}, {"time": "2025-07-08", "position": "aboveBar", "color": "#4caf50", "shape": "arrowDown", "text": "V27 +2.6%", "size": 1, "method": "v27"}, {"time": "2025-07-17", "position": "belowBar", "color": "#9C27B0", "shape": "arrowUp", "text": "V27 Buy", "size": 1, "method": "v27"}, {"time": "2025-08-04", "position": "aboveBar", "color": "#f44336", "shape": "arrowDown", "text": "V27 -3.7%", "size": 1, "method": "v27"}], "v27_trades": [{"entry_date": "2021-03-19", "exit_date": "2021-04-22", "pnl_pct": -3.29, "holding_days": 23, "exit_reason": "signal", "entry_trend": "moderate", "quick_reentry": false, "breakout_entry": false, "vshape_entry": false, "entry_profile": "balanced", "entry_choppy_regime": false, "position_size": 0.25}, {"entry_date": "2021-06-17", "exit_date": "2021-07-01", "pnl_pct": -7.17, "holding_days": 10, "exit_reason": "signal", "entry_trend": "moderate", "quick_reentry": false, "breakout_entry": false, "vshape_entry": false, "entry_profile": "balanced", "entry_choppy_regime": false, "position_size": 0.25}, {"entry_date": "2021-09-10", "exit_date": "2021-10-11", "pnl_pct": 6.47, "holding_days": 21, "exit_reason": "signal", "entry_trend": "strong", "quick_reentry": false, "breakout_entry": false, "vshape_entry": false, "entry_profile": "balanced", "entry_choppy_regime": false, "position_size": 0.25}, {"entry_date": "2021-10-19", "exit_date": "2021-11-09", "pnl_pct": -0.59, "holding_days": 15, "exit_reason": "signal", "entry_trend": "strong", "quick_reentry": false, "breakout_entry": false, "vshape_entry": false, "entry_profile": "balanced", "entry_choppy_regime": false, "position_size": 0.425}, {"entry_date": "2021-11-15", "exit_date": "2021-11-24", "pnl_pct": -12.62, "holding_days": 7, "exit_reason": "signal_hard_cap", "entry_trend": "strong", "quick_reentry": false, "breakout_entry": false, "vshape_entry": false, "entry_profile": "balanced", "entry_choppy_regime": false, "position_size": 0.34}, {"entry_date": "2022-02-22", "exit_date": "2022-03-28", "pnl_pct": -2.36, "holding_days": 24, "exit_reason": "signal", "entry_trend": "weak", "quick_reentry": false, "breakout_entry": false, "vshape_entry": false, "entry_profile": "balanced", "entry_choppy_regime": false, "position_size": 0.25}, {"entry_date": "2022-05-20", "exit_date": "2022-06-17", "pnl_pct": 1.04, "holding_days": 20, "exit_reason": "signal", "entry_trend": "weak", "quick_reentry": false, "breakout_entry": false, "vshape_entry": true, "entry_profile": "balanced", "entry_choppy_regime": false, "position_size": 0.26775}, {"entry_date": "2023-02-03", "exit_date": "2023-04-10", "pnl_pct": 54.26, "holding_days": 46, "exit_reason": "signal", "entry_trend": "weak", "quick_reentry": false, "breakout_entry": false, "vshape_entry": false, "entry_profile": "balanced", "entry_choppy_regime": false, "position_size": 0.25}, {"entry_date": "2023-05-16", "exit_date": "2023-06-20", "pnl_pct": 5.79, "holding_days": 25, "exit_reason": "signal", "entry_trend": "moderate", "quick_reentry": false, "breakout_entry": false, "vshape_entry": false, "entry_profile": "balanced", "entry_choppy_regime": false, "position_size": 0.25}, {"entry_date": "2023-08-04", "exit_date": "2023-08-28", "pnl_pct": 0.82, "holding_days": 16, "exit_reason": "signal", "entry_trend": "strong", "quick_reentry": false, "breakout_entry": false, "vshape_entry": false, "entry_profile": "balanced", "entry_choppy_regime": false, "position_size": 0.9}, {"entry_date": "2023-12-07", "exit_date": "2023-12-21", "pnl_pct": -1.88, "holding_days": 10, "exit_reason": "signal", "entry_trend": "moderate", "quick_reentry": false, "breakout_entry": false, "vshape_entry": false, "entry_profile": "balanced", "entry_choppy_regime": false, "position_size": 0.3375}, {"entry_date": "2024-02-22", "exit_date": "2024-03-07", "pnl_pct": -1.86, "holding_days": 10, "exit_reason": "signal", "entry_trend": "strong", "quick_reentry": false, "breakout_entry": false, "vshape_entry": false, "entry_profile": "balanced", "entry_choppy_regime": false, "position_size": 0.31875}, {"entry_date": "2024-03-25", "exit_date": "2024-04-22", "pnl_pct": -0.98, "holding_days": 19, "exit_reason": "signal", "entry_trend": "strong", "quick_reentry": false, "breakout_entry": false, "vshape_entry": false, "entry_profile": "balanced", "entry_choppy_regime": false, "position_size": 0.31875}, {"entry_date": "2024-06-17", "exit_date": "2024-07-04", "pnl_pct": 6.42, "holding_days": 13, "exit_reason": "signal", "entry_trend": "strong", "quick_reentry": false, "breakout_entry": false, "vshape_entry": false, "entry_profile": "balanced", "entry_choppy_regime": false, "position_size": 0.31875}, {"entry_date": "2024-07-09", "exit_date": "2024-07-26", "pnl_pct": -9.79, "holding_days": 13, "exit_reason": "signal", "entry_trend": "strong", "quick_reentry": false, "breakout_entry": false, "vshape_entry": false, "entry_profile": "balanced", "entry_choppy_regime": false, "position_size": 0.26775}, {"entry_date": "2025-02-25", "exit_date": "2025-03-10", "pnl_pct": -6.74, "holding_days": 9, "exit_reason": "signal", "entry_trend": "strong", "quick_reentry": false, "breakout_entry": false, "vshape_entry": false, "entry_profile": "balanced", "entry_choppy_regime": false, "position_size": 0.25}, {"entry_date": "2025-04-11", "exit_date": "2025-04-22", "pnl_pct": -11.84, "holding_days": 7, "exit_reason": "signal_hard_cap", "entry_trend": "weak", "quick_reentry": false, "breakout_entry": false, "vshape_entry": true, "entry_profile": "balanced", "entry_choppy_regime": false, "position_size": 0.26775}, {"entry_date": "2025-06-16", "exit_date": "2025-07-08", "pnl_pct": 2.63, "holding_days": 16, "exit_reason": "signal", "entry_trend": "strong", "quick_reentry": false, "breakout_entry": false, "vshape_entry": false, "entry_profile": "balanced", "entry_choppy_regime": false, "position_size": 0.31875}, {"entry_date": "2025-07-17", "exit_date": "2025-08-04", "pnl_pct": -3.66, "holding_days": 12, "exit_reason": "signal", "entry_trend": "moderate", "quick_reentry": false, "breakout_entry": false, "vshape_entry": false, "entry_profile": "balanced", "entry_choppy_regime": false, "position_size": 0.25}], "v27_stats": {"total_trades": 19, "wins": 7, "losses": 12, "win_rate": 36.8, "total_pnl_pct": 14.6, "avg_pnl_pct": 0.77, "median_pnl_pct": -1.86, "std_pnl_pct": 13.74, "avg_win_pct": 11.06, "avg_loss_pct": -5.23, "payoff_ratio": 2.11, "max_win_pct": 54.26, "max_loss_pct": -12.62, "avg_hold": 16.6, "pf": 1.23, "version": "v27"}}