{"symbol": "TIG", "v19_1_markers": [{"time": "2020-02-07", "position": "belowBar", "color": "#26C6DA", "shape": "arrowUp", "text": "V19.1 Buy", "size": 1, "method": "v19_1"}, {"time": "2020-03-13", "position": "aboveBar", "color": "#4caf50", "shape": "arrowDown", "text": "V19.1 +0.0%", "size": 1, "method": "v19_1"}, {"time": "2020-06-02", "position": "belowBar", "color": "#26C6DA", "shape": "arrowUp", "text": "V19.1 Buy", "size": 1, "method": "v19_1"}, {"time": "2020-07-20", "position": "aboveBar", "color": "#4caf50", "shape": "arrowDown", "text": "V19.1 +9.2% PE", "size": 1, "method": "v19_1"}, {"time": "2020-08-28", "position": "belowBar", "color": "#26C6DA", "shape": "arrowUp", "text": "V19.1 Buy", "size": 1, "method": "v19_1"}, {"time": "2020-10-14", "position": "aboveBar", "color": "#4caf50", "shape": "arrowDown", "text": "V19.1 +4.6%", "size": 1, "method": "v19_1"}, {"time": "2020-12-18", "position": "belowBar", "color": "#26C6DA", "shape": "arrowUp", "text": "V19.1 Buy", "size": 1, "method": "v19_1"}, {"time": "2020-12-31", "position": "aboveBar", "color": "#4caf50", "shape": "arrowDown", "text": "V19.1 +18.7% END", "size": 1, "method": "v19_1"}, {"time": "2021-01-06", "position": "belowBar", "color": "#26C6DA", "shape": "arrowUp", "text": "V19.1 Buy", "size": 1, "method": "v19_1"}, {"time": "2021-01-22", "position": "aboveBar", "color": "#4caf50", "shape": "arrowDown", "text": "V19.1 +1.1% TS", "size": 1, "method": "v19_1"}, {"time": "2021-01-25", "position": "belowBar", "color": "#26C6DA", "shape": "arrowUp", "text": "V19.1 Buy", "size": 1, "method": "v19_1"}, {"time": "2021-02-08", "position": "aboveBar", "color": "#f44336", "shape": "arrowDown", "text": "V19.1 -17.4%", "size": 1, "method": "v19_1"}, {"time": "2021-02-25", "position": "belowBar", "color": "#26C6DA", "shape": "arrowUp", "text": "V19.1 Buy", "size": 1, "method": "v19_1"}, {"time": "2021-03-23", "position": "aboveBar", "color": "#4caf50", "shape": "arrowDown", "text": "V19.1 +7.3%", "size": 1, "method": "v19_1"}, {"time": "2021-03-31", "position": "belowBar", "color": "#26C6DA", "shape": "arrowUp", "text": "V19.1 Buy", "size": 1, "method": "v19_1"}, {"time": "2021-06-10", "position": "aboveBar", "color": "#4caf50", "shape": "arrowDown", "text": "V19.1 +42.2%", "size": 1, "method": "v19_1"}, {"time": "2021-08-16", "position": "belowBar", "color": "#26C6DA", "shape": "arrowUp", "text": "V19.1 Buy", "size": 1, "method": "v19_1"}, {"time": "2021-12-31", "position": "aboveBar", "color": "#4caf50", "shape": "arrowDown", "text": "V19.1 +88.0% END", "size": 1, "method": "v19_1"}, {"time": "2022-02-22", "position": "belowBar", "color": "#26C6DA", "shape": "arrowUp", "text": "V19.1 Buy", "size": 1, "method": "v19_1"}, {"time": "2022-03-16", "position": "aboveBar", "color": "#f44336", "shape": "arrowDown", "text": "V19.1 -2.8%", "size": 1, "method": "v19_1"}, {"time": "2022-03-22", "position": "belowBar", "color": "#26C6DA", "shape": "arrowUp", "text": "V19.1 Buy", "size": 1, "method": "v19_1"}, {"time": "2022-04-14", "position": "aboveBar", "color": "#4caf50", "shape": "arrowDown", "text": "V19.1 +1.7%", "size": 1, "method": "v19_1"}, {"time": "2022-07-08", "position": "belowBar", "color": "#26C6DA", "shape": "arrowUp", "text": "V19.1 Buy", "size": 1, "method": "v19_1"}, {"time": "2022-07-27", "position": "aboveBar", "color": "#4caf50", "shape": "arrowDown", "text": "V19.1 +1.7%", "size": 1, "method": "v19_1"}, {"time": "2022-08-11", "position": "belowBar", "color": "#26C6DA", "shape": "arrowUp", "text": "V19.1 Buy", "size": 1, "method": "v19_1"}, {"time": "2022-08-24", "position": "aboveBar", "color": "#f44336", "shape": "arrowDown", "text": "V19.1 -2.1%", "size": 1, "method": "v19_1"}, {"time": "2022-10-05", "position": "belowBar", "color": "#26C6DA", "shape": "arrowUp", "text": "V19.1 Buy", "size": 1, "method": "v19_1"}, {"time": "2022-10-19", "position": "aboveBar", "color": "#f44336", "shape": "arrowDown", "text": "V19.1 -10.9%", "size": 1, "method": "v19_1"}, {"time": "2022-11-17", "position": "belowBar", "color": "#26C6DA", "shape": "arrowUp", "text": "V19.1 Buy", "size": 1, "method": "v19_1"}, {"time": "2022-12-28", "position": "aboveBar", "color": "#4caf50", "shape": "arrowDown", "text": "V19.1 +42.1%", "size": 1, "method": "v19_1"}, {"time": "2023-02-02", "position": "belowBar", "color": "#26C6DA", "shape": "arrowUp", "text": "V19.1 Buy", "size": 1, "method": "v19_1"}, {"time": "2023-02-23", "position": "aboveBar", "color": "#f44336", "shape": "arrowDown", "text": "V19.1 -1.2%", "size": 1, "method": "v19_1"}, {"time": "2023-05-08", "position": "belowBar", "color": "#26C6DA", "shape": "arrowUp", "text": "V19.1 Buy", "size": 1, "method": "v19_1"}, {"time": "2023-06-08", "position": "aboveBar", "color": "#4caf50", "shape": "arrowDown", "text": "V19.1 +21.8% PP", "size": 1, "method": "v19_1"}, {"time": "2023-06-23", "position": "belowBar", "color": "#26C6DA", "shape": "arrowUp", "text": "V19.1 Buy", "size": 1, "method": "v19_1"}, {"time": "2023-07-07", "position": "aboveBar", "color": "#f44336", "shape": "arrowDown", "text": "V19.1 -4.4%", "size": 1, "method": "v19_1"}, {"time": "2023-07-13", "position": "belowBar", "color": "#26C6DA", "shape": "arrowUp", "text": "V19.1 Buy", "size": 1, "method": "v19_1"}, {"time": "2023-08-18", "position": "aboveBar", "color": "#f44336", "shape": "arrowDown", "text": "V19.1 -9.8%", "size": 1, "method": "v19_1"}, {"time": "2023-09-11", "position": "belowBar", "color": "#26C6DA", "shape": "arrowUp", "text": "V19.1 Buy", "size": 1, "method": "v19_1"}, {"time": "2023-09-25", "position": "aboveBar", "color": "#f44336", "shape": "arrowDown", "text": "V19.1 -13.7%", "size": 1, "method": "v19_1"}, {"time": "2023-10-03", "position": "belowBar", "color": "#26C6DA", "shape": "arrowUp", "text": "V19.1 Buy", "size": 1, "method": "v19_1"}, {"time": "2023-10-19", "position": "aboveBar", "color": "#f44336", "shape": "arrowDown", "text": "V19.1 -2.8%", "size": 1, "method": "v19_1"}, {"time": "2023-11-21", "position": "belowBar", "color": "#26C6DA", "shape": "arrowUp", "text": "V19.1 Buy", "size": 1, "method": "v19_1"}, {"time": "2023-12-19", "position": "aboveBar", "color": "#4caf50", "shape": "arrowDown", "text": "V19.1 +12.8% PP", "size": 1, "method": "v19_1"}, {"time": "2024-02-20", "position": "belowBar", "color": "#26C6DA", "shape": "arrowUp", "text": "V19.1 Buy", "size": 1, "method": "v19_1"}, {"time": "2024-04-04", "position": "aboveBar", "color": "#4caf50", "shape": "arrowDown", "text": "V19.1 +8.2%", "size": 1, "method": "v19_1"}, {"time": "2024-05-09", "position": "belowBar", "color": "#26C6DA", "shape": "arrowUp", "text": "V19.1 Buy", "size": 1, "method": "v19_1"}, {"time": "2024-05-30", "position": "aboveBar", "color": "#4caf50", "shape": "arrowDown", "text": "V19.1 +12.8% PE", "size": 1, "method": "v19_1"}, {"time": "2024-06-11", "position": "belowBar", "color": "#26C6DA", "shape": "arrowUp", "text": "V19.1 Buy", "size": 1, "method": "v19_1"}, {"time": "2024-06-24", "position": "aboveBar", "color": "#f44336", "shape": "arrowDown", "text": "V19.1 -11.7%", "size": 1, "method": "v19_1"}, {"time": "2024-07-08", "position": "belowBar", "color": "#26C6DA", "shape": "arrowUp", "text": "V19.1 Buy", "size": 1, "method": "v19_1"}, {"time": "2024-07-25", "position": "aboveBar", "color": "#f44336", "shape": "arrowDown", "text": "V19.1 -5.7%", "size": 1, "method": "v19_1"}, {"time": "2024-08-16", "position": "belowBar", "color": "#26C6DA", "shape": "arrowUp", "text": "V19.1 Buy", "size": 1, "method": "v19_1"}, {"time": "2024-09-13", "position": "aboveBar", "color": "#f44336", "shape": "arrowDown", "text": "V19.1 -3.7%", "size": 1, "method": "v19_1"}, {"time": "2024-09-20", "position": "belowBar", "color": "#26C6DA", "shape": "arrowUp", "text": "V19.1 Buy", "size": 1, "method": "v19_1"}, {"time": "2024-10-07", "position": "aboveBar", "color": "#f44336", "shape": "arrowDown", "text": "V19.1 -2.9%", "size": 1, "method": "v19_1"}, {"time": "2024-12-03", "position": "belowBar", "color": "#26C6DA", "shape": "arrowUp", "text": "V19.1 Buy", "size": 1, "method": "v19_1"}, {"time": "2024-12-18", "position": "aboveBar", "color": "#f44336", "shape": "arrowDown", "text": "V19.1 -1.5%", "size": 1, "method": "v19_1"}, {"time": "2025-06-02", "position": "belowBar", "color": "#26C6DA", "shape": "arrowUp", "text": "V19.1 Buy", "size": 1, "method": "v19_1"}, {"time": "2025-06-18", "position": "aboveBar", "color": "#f44336", "shape": "arrowDown", "text": "V19.1 -4.0%", "size": 1, "method": "v19_1"}, {"time": "2025-07-10", "position": "belowBar", "color": "#26C6DA", "shape": "arrowUp", "text": "V19.1 Buy", "size": 1, "method": "v19_1"}, {"time": "2025-09-08", "position": "aboveBar", "color": "#4caf50", "shape": "arrowDown", "text": "V19.1 +23.7% PP", "size": 1, "method": "v19_1"}, {"time": "2025-10-28", "position": "belowBar", "color": "#26C6DA", "shape": "arrowUp", "text": "V19.1 Buy", "size": 1, "method": "v19_1"}, {"time": "2025-11-10", "position": "aboveBar", "color": "#f44336", "shape": "arrowDown", "text": "V19.1 -6.2%", "size": 1, "method": "v19_1"}, {"time": "2025-12-15", "position": "belowBar", "color": "#26C6DA", "shape": "arrowUp", "text": "V19.1 Buy", "size": 1, "method": "v19_1"}, {"time": "2025-12-31", "position": "aboveBar", "color": "#4caf50", "shape": "arrowDown", "text": "V19.1 +4.9% END", "size": 1, "method": "v19_1"}], "v19_1_trades": [{"entry_date": "2020-02-07", "exit_date": "2020-03-13", "pnl_pct": 0.0, "holding_days": 23, "exit_reason": "signal", "entry_trend": "weak", "quick_reentry": false, "breakout_entry": false, "vshape_entry": true, "entry_profile": "balanced", "entry_choppy_regime": false, "position_size": 0.51}, {"entry_date": "2020-06-02", "exit_date": "2020-07-20", "pnl_pct": 9.23, "holding_days": 34, "exit_reason": "peak_protect_ema", "entry_trend": "strong", "quick_reentry": false, "breakout_entry": false, "vshape_entry": false, "entry_profile": "balanced", "entry_choppy_regime": false, "position_size": 0.425}, {"entry_date": "2020-08-28", "exit_date": "2020-10-14", "pnl_pct": 4.56, "holding_days": 29, "exit_reason": "signal", "entry_trend": "weak", "quick_reentry": false, "breakout_entry": false, "vshape_entry": false, "entry_profile": "balanced", "entry_choppy_regime": false, "position_size": 0.7}, {"entry_date": "2020-12-18", "exit_date": "2020-12-31", "pnl_pct": 18.69, "holding_days": 9, "exit_reason": "end", "entry_trend": "strong", "quick_reentry": false, "breakout_entry": false, "vshape_entry": false, "entry_profile": "balanced", "entry_choppy_regime": false, "position_size": 0.5}, {"entry_date": "2021-01-06", "exit_date": "2021-01-22", "pnl_pct": 1.15, "holding_days": 12, "exit_reason": "trailing_stop", "entry_trend": "weak", "quick_reentry": false, "breakout_entry": false, "vshape_entry": false, "entry_profile": "balanced", "entry_choppy_regime": false, "position_size": 0.7}, {"entry_date": "2021-01-25", "exit_date": "2021-02-08", "pnl_pct": -17.39, "holding_days": 10, "exit_reason": "signal", "entry_trend": "moderate", "quick_reentry": true, "breakout_entry": false, "vshape_entry": false, "entry_profile": "balanced", "entry_choppy_regime": false, "position_size": 0.3825}, {"entry_date": "2021-02-25", "exit_date": "2021-03-23", "pnl_pct": 7.3, "holding_days": 18, "exit_reason": "signal", "entry_trend": "moderate", "quick_reentry": false, "breakout_entry": false, "vshape_entry": false, "entry_profile": "balanced", "entry_choppy_regime": false, "position_size": 0.3825}, {"entry_date": "2021-03-31", "exit_date": "2021-06-10", "pnl_pct": 42.23, "holding_days": 46, "exit_reason": "signal", "entry_trend": "strong", "quick_reentry": false, "breakout_entry": false, "vshape_entry": false, "entry_profile": "balanced", "entry_choppy_regime": false, "position_size": 0.425}, {"entry_date": "2021-08-16", "exit_date": "2021-12-31", "pnl_pct": 87.96, "holding_days": 95, "exit_reason": "end", "entry_trend": "strong", "quick_reentry": false, "breakout_entry": false, "vshape_entry": false, "entry_profile": "balanced", "entry_choppy_regime": false, "position_size": 0.425}, {"entry_date": "2022-02-22", "exit_date": "2022-03-16", "pnl_pct": -2.84, "holding_days": 16, "exit_reason": "signal", "entry_trend": "strong", "quick_reentry": false, "breakout_entry": false, "vshape_entry": false, "entry_profile": "balanced", "entry_choppy_regime": false, "position_size": 0.5}, {"entry_date": "2022-03-22", "exit_date": "2022-04-14", "pnl_pct": 1.74, "holding_days": 16, "exit_reason": "signal", "entry_trend": "strong", "quick_reentry": false, "breakout_entry": false, "vshape_entry": false, "entry_profile": "balanced", "entry_choppy_regime": false, "position_size": 0.7}, {"entry_date": "2022-07-08", "exit_date": "2022-07-27", "pnl_pct": 1.7, "holding_days": 13, "exit_reason": "signal", "entry_trend": "weak", "quick_reentry": false, "breakout_entry": false, "vshape_entry": true, "entry_profile": "balanced", "entry_choppy_regime": false, "position_size": 0.4589999999999999}, {"entry_date": "2022-08-11", "exit_date": "2022-08-24", "pnl_pct": -2.12, "holding_days": 9, "exit_reason": "signal", "entry_trend": "moderate", "quick_reentry": false, "breakout_entry": false, "vshape_entry": false, "entry_profile": "balanced", "entry_choppy_regime": false, "position_size": 0.425}, {"entry_date": "2022-10-05", "exit_date": "2022-10-19", "pnl_pct": -10.9, "holding_days": 10, "exit_reason": "signal", "entry_trend": "weak", "quick_reentry": false, "breakout_entry": false, "vshape_entry": true, "entry_profile": "balanced", "entry_choppy_regime": false, "position_size": 0.4589999999999999}, {"entry_date": "2022-11-17", "exit_date": "2022-12-28", "pnl_pct": 42.08, "holding_days": 29, "exit_reason": "signal", "entry_trend": "weak", "quick_reentry": false, "breakout_entry": false, "vshape_entry": true, "entry_profile": "balanced", "entry_choppy_regime": false, "position_size": 0.4589999999999999}, {"entry_date": "2023-02-02", "exit_date": "2023-02-23", "pnl_pct": -1.16, "holding_days": 15, "exit_reason": "signal", "entry_trend": "moderate", "quick_reentry": false, "breakout_entry": false, "vshape_entry": false, "entry_profile": "balanced", "entry_choppy_regime": false, "position_size": 0.5355}, {"entry_date": "2023-05-08", "exit_date": "2023-06-08", "pnl_pct": 21.77, "holding_days": 23, "exit_reason": "peak_protect_dist", "entry_trend": "strong", "quick_reentry": false, "breakout_entry": true, "vshape_entry": false, "entry_profile": "balanced", "entry_choppy_regime": false, "position_size": 0.5}, {"entry_date": "2023-06-23", "exit_date": "2023-07-07", "pnl_pct": -4.36, "holding_days": 10, "exit_reason": "signal", "entry_trend": "strong", "quick_reentry": false, "breakout_entry": false, "vshape_entry": false, "entry_profile": "balanced", "entry_choppy_regime": false, "position_size": 0.595}, {"entry_date": "2023-07-13", "exit_date": "2023-08-18", "pnl_pct": -9.83, "holding_days": 26, "exit_reason": "signal", "entry_trend": "strong", "quick_reentry": false, "breakout_entry": false, "vshape_entry": false, "entry_profile": "balanced", "entry_choppy_regime": false, "position_size": 0.5}, {"entry_date": "2023-09-11", "exit_date": "2023-09-25", "pnl_pct": -13.72, "holding_days": 10, "exit_reason": "signal", "entry_trend": "weak", "quick_reentry": false, "breakout_entry": false, "vshape_entry": false, "entry_profile": "balanced", "entry_choppy_regime": false, "position_size": 0.4899999999999999}, {"entry_date": "2023-10-03", "exit_date": "2023-10-19", "pnl_pct": -2.75, "holding_days": 12, "exit_reason": "signal", "entry_trend": "weak", "quick_reentry": false, "breakout_entry": false, "vshape_entry": true, "entry_profile": "balanced", "entry_choppy_regime": false, "position_size": 0.3825}, {"entry_date": "2023-11-21", "exit_date": "2023-12-19", "pnl_pct": 12.78, "holding_days": 19, "exit_reason": "peak_protect_dist", "entry_trend": "strong", "quick_reentry": false, "breakout_entry": false, "vshape_entry": false, "entry_profile": "balanced", "entry_choppy_regime": false, "position_size": 0.425}, {"entry_date": "2024-02-20", "exit_date": "2024-04-04", "pnl_pct": 8.2, "holding_days": 32, "exit_reason": "signal", "entry_trend": "moderate", "quick_reentry": false, "breakout_entry": false, "vshape_entry": false, "entry_profile": "balanced", "entry_choppy_regime": false, "position_size": 0.7}, {"entry_date": "2024-05-09", "exit_date": "2024-05-30", "pnl_pct": 12.8, "holding_days": 15, "exit_reason": "peak_protect_ema", "entry_trend": "weak", "quick_reentry": false, "breakout_entry": false, "vshape_entry": false, "entry_profile": "balanced", "entry_choppy_regime": false, "position_size": 0.595}, {"entry_date": "2024-06-11", "exit_date": "2024-06-24", "pnl_pct": -11.66, "holding_days": 9, "exit_reason": "signal", "entry_trend": "strong", "quick_reentry": false, "breakout_entry": false, "vshape_entry": false, "entry_profile": "balanced", "entry_choppy_regime": false, "position_size": 0.425}, {"entry_date": "2024-07-08", "exit_date": "2024-07-25", "pnl_pct": -5.73, "holding_days": 13, "exit_reason": "signal", "entry_trend": "strong", "quick_reentry": false, "breakout_entry": false, "vshape_entry": false, "entry_profile": "balanced", "entry_choppy_regime": false, "position_size": 0.7}, {"entry_date": "2024-08-16", "exit_date": "2024-09-13", "pnl_pct": -3.68, "holding_days": 18, "exit_reason": "signal", "entry_trend": "weak", "quick_reentry": false, "breakout_entry": false, "vshape_entry": true, "entry_profile": "balanced", "entry_choppy_regime": false, "position_size": 0.34425}, {"entry_date": "2024-09-20", "exit_date": "2024-10-07", "pnl_pct": -2.94, "holding_days": 11, "exit_reason": "signal", "entry_trend": "weak", "quick_reentry": false, "breakout_entry": false, "vshape_entry": false, "entry_profile": "balanced", "entry_choppy_regime": true, "position_size": 0.65}, {"entry_date": "2024-12-03", "exit_date": "2024-12-18", "pnl_pct": -1.47, "holding_days": 11, "exit_reason": "signal", "entry_trend": "moderate", "quick_reentry": false, "breakout_entry": false, "vshape_entry": false, "entry_profile": "balanced", "entry_choppy_regime": false, "position_size": 0.7}, {"entry_date": "2025-06-02", "exit_date": "2025-06-18", "pnl_pct": -4.0, "holding_days": 12, "exit_reason": "signal", "entry_trend": "weak", "quick_reentry": false, "breakout_entry": false, "vshape_entry": true, "entry_profile": "balanced", "entry_choppy_regime": false, "position_size": 0.3825}, {"entry_date": "2025-07-10", "exit_date": "2025-09-08", "pnl_pct": 23.68, "holding_days": 40, "exit_reason": "peak_protect_dist", "entry_trend": "weak", "quick_reentry": false, "breakout_entry": false, "vshape_entry": false, "entry_profile": "balanced", "entry_choppy_regime": true, "position_size": 0.325}, {"entry_date": "2025-10-28", "exit_date": "2025-11-10", "pnl_pct": -6.25, "holding_days": 9, "exit_reason": "signal", "entry_trend": "weak", "quick_reentry": false, "breakout_entry": false, "vshape_entry": true, "entry_profile": "balanced", "entry_choppy_regime": false, "position_size": 0.51}, {"entry_date": "2025-12-15", "exit_date": "2025-12-31", "pnl_pct": 4.94, "holding_days": 12, "exit_reason": "end", "entry_trend": "weak", "quick_reentry": false, "breakout_entry": true, "vshape_entry": false, "entry_profile": "balanced", "entry_choppy_regime": true, "position_size": 0.65}], "v19_1_stats": {"total_trades": 33, "wins": 16, "losses": 17, "win_rate": 48.5, "total_pnl_pct": 200.0, "avg_pnl_pct": 6.06, "median_pnl_pct": 0.0, "std_pnl_pct": 19.88, "avg_win_pct": 18.8, "avg_loss_pct": -5.93, "payoff_ratio": 3.17, "max_win_pct": 87.96, "max_loss_pct": -17.39, "avg_hold": 20.2, "pf": 2.98, "version": "v19_1"}}